bvlogger/__init__.py
bvlogger/authentication.py
bvlogger/connector_logging.py
bvlogger/endpoint_details.py
bvlogger-1.0.10.dist-info/METADATA
bvlogger-1.0.10.dist-info/WHEEL
bvlogger-1.0.10.dist-info/top_level.txt
bvlogger-1.0.10.dist-info/RECORD
