Metadata-Version: 2.1
Name: bvlogger
Version: 1.0.10
Summary: A brief description of your project
Home-page: https://github.com/obaidshk/bvlogger
Author: Your Name
Author-email: your.email@example.com
Classifier: Programming Language :: Python :: 3
Classifier: License :: OSI Approved :: MIT License
Classifier: Operating System :: OS Independent
